setup.py
opensm/__init__.py
opensm/devicecontroller.py
opensm/osm.py
opensm.egg-info/PKG-INFO
opensm.egg-info/SOURCES.txt
opensm.egg-info/dependency_links.txt
opensm.egg-info/entry_points.txt
opensm.egg-info/not-zip-safe
opensm.egg-info/requires.txt
opensm.egg-info/top_level.txt