Metadata-Version: 1.1
Name: opensm
Version: 0.1.3
Summary: Sound mixer
Home-page: http://github.com/isivisi/opensoundmixer
Author: John Iannandrea
Author-email: jiannandrea@gmail.com
License: GNU
Keywords: sound mixer
Platform: UNKNOWN
Classifier: Programming Language :: Python :: 3.5
Classifier: Operating System :: OS Independent
